{
  "version": "1.0.0.0",
  "strings": {
    "name": "Webové rozhraní API pro ASP.NET Core",
    "description": "Šablona projektu pro vytvoření webového rozhraní RESTful API s využitím kontrolerů ASP.NET Core nebo minimálních rozhraní API s volitelnou podporou OpenAPI a ověřování.",
    "parameter.DisableOpenAPI.name": "Povolit podporu _OpenAPI",
    "parameter.DisableOpenAPI.description": "Povolení podpory OpenAPI (Swagger)",
    "parameter.UseMinimalAPIs.name": "Použití ovladačů",
    "parameter.UseMinimalAPIs.description": "Místo minimálních rozhraní API používejte kontrolery."
  }
}