{
  "AssemblyIdentity": "PageGenerator, Version=1.0.0.0, Culture=neutral, PublicKeyToken=adb9793829ddae60",
  "Types": [
    {
      "Name": "PageGenerator.Program",
      "Visibility": "Public",
      "Kind": "Class",
      "ImplementedInterfaces": [],
      "Members": [
        {
          "Kind": "Method",
          "Name": "Main",
          "Parameters": [
            {
              "Name": "args",
              "Type": "System.String[]"
            }
          ],
          "ReturnType": "System.Void",
          "Static": true,
          "Visibility": "Public",
          "GenericParameter": []
        },
        {
          "Kind": "Constructor",
          "Name": ".ctor",
          "Parameters": [],
          "Visibility": "Public",
          "GenericParameter": []
        }
      ],
      "GenericParameters": []
    }
  ]
}