{
  "AssemblyIdentity": "Microsoft.AspNetCore.ResponseCaching, Version=2.1.1.0, Culture=neutral, PublicKeyToken=adb9793829ddae60",
  "Types": [
    {
      "Name": "Microsoft.Extensions.DependencyInjection.ResponseCachingServicesExtensions",
      "Visibility": "Public",
      "Kind": "Class",
      "Abstract": true,
      "Static": true,
      "Sealed": true,
      "ImplementedInterfaces": [],
      "Members": [
        {
          "Kind": "Method",
          "Name": "AddResponseCaching",
          "Parameters": [
            {
              "Name": "services",
              "Type": "Microsoft.Extensions.DependencyInjection.IServiceCollection"
            }
          ],
          "ReturnType": "Microsoft.Extensions.DependencyInjection.IServiceCollection",
          "Static": true,
          "Extension": true,
          "Visibility": "Public",
          "GenericParameter": []
        },
        {
          "Kind": "Method",
          "Name": "AddResponseCaching",
          "Parameters": [
            {
              "Name": "services",
              "Type": "Microsoft.Extensions.DependencyInjection.IServiceCollection"
            },
            {
              "Name": "configureOptions",
              "Type": "System.Action<Microsoft.AspNetCore.ResponseCaching.ResponseCachingOptions>"
            }
          ],
          "ReturnType": "Microsoft.Extensions.DependencyInjection.IServiceCollection",
          "Static": true,
          "Extension": true,
          "Visibility": "Public",
          "GenericParameter": []
        }
      ],
      "GenericParameters": []
    },
    {
      "Name": "Microsoft.AspNetCore.Builder.ResponseCachingExtensions",
      "Visibility": "Public",
      "Kind": "Class",
      "Abstract": true,
      "Static": true,
      "Sealed": true,
      "ImplementedInterfaces": [],
      "Members": [
        {
          "Kind": "Method",
          "Name": "UseResponseCaching",
          "Parameters": [
            {
              "Name": "app",
              "Type": "Microsoft.AspNetCore.Builder.IApplicationBuilder"
            }
          ],
          "ReturnType": "Microsoft.AspNetCore.Builder.IApplicationBuilder",
          "Static": true,
          "Extension": true,
          "Visibility": "Public",
          "GenericParameter": []
        }
      ],
      "GenericParameters": []
    },
    {
      "Name": "Microsoft.AspNetCore.ResponseCaching.ResponseCachingFeature",
      "Visibility": "Public",
      "Kind": "Class",
      "ImplementedInterfaces": [
        "Microsoft.AspNetCore.ResponseCaching.IResponseCachingFeature"
      ],
      "Members": [
        {
          "Kind": "Method",
          "Name": "get_VaryByQueryKeys",
          "Parameters": [],
          "ReturnType": "System.String[]",
          "Sealed": true,
          "Virtual": true,
          "ImplementedInterface": "Microsoft.AspNetCore.ResponseCaching.IResponseCachingFeature",
          "Visibility": "Public",
          "GenericParameter": []
        },
        {
          "Kind": "Method",
          "Name": "set_VaryByQueryKeys",
          "Parameters": [
            {
              "Name": "value",
              "Type": "System.String[]"
            }
          ],
          "ReturnType": "System.Void",
          "Sealed": true,
          "Virtual": true,
          "ImplementedInterface": "Microsoft.AspNetCore.ResponseCaching.IResponseCachingFeature",
          "Visibility": "Public",
          "GenericParameter": []
        },
        {
          "Kind": "Constructor",
          "Name": ".ctor",
          "Parameters": [],
          "Visibility": "Public",
          "GenericParameter": []
        }
      ],
      "GenericParameters": []
    },
    {
      "Name": "Microsoft.AspNetCore.ResponseCaching.ResponseCachingMiddleware",
      "Visibility": "Public",
      "Kind": "Class",
      "ImplementedInterfaces": [],
      "Members": [
        {
          "Kind": "Method",
          "Name": "Invoke",
          "Parameters": [
            {
              "Name": "httpContext",
              "Type": "Microsoft.AspNetCore.Http.HttpContext"
            }
          ],
          "ReturnType": "System.Threading.Tasks.Task",
          "Visibility": "Public",
          "GenericParameter": []
        },
        {
          "Kind": "Constructor",
          "Name": ".ctor",
          "Parameters": [
            {
              "Name": "next",
              "Type": "Microsoft.AspNetCore.Http.RequestDelegate"
            },
            {
              "Name": "options",
              "Type": "Microsoft.Extensions.Options.IOptions<Microsoft.AspNetCore.ResponseCaching.ResponseCachingOptions>"
            },
            {
              "Name": "loggerFactory",
              "Type": "Microsoft.Extensions.Logging.ILoggerFactory"
            },
            {
              "Name": "policyProvider",
              "Type": "Microsoft.AspNetCore.ResponseCaching.Internal.IResponseCachingPolicyProvider"
            },
            {
              "Name": "keyProvider",
              "Type": "Microsoft.AspNetCore.ResponseCaching.Internal.IResponseCachingKeyProvider"
            }
          ],
          "Visibility": "Public",
          "GenericParameter": []
        }
      ],
      "GenericParameters": []
    },
    {
      "Name": "Microsoft.AspNetCore.ResponseCaching.ResponseCachingOptions",
      "Visibility": "Public",
      "Kind": "Class",
      "ImplementedInterfaces": [],
      "Members": [
        {
          "Kind": "Method",
          "Name": "get_SizeLimit",
          "Parameters": [],
          "ReturnType": "System.Int64",
          "Visibility": "Public",
          "GenericParameter": []
        },
        {
          "Kind": "Method",
          "Name": "set_SizeLimit",
          "Parameters": [
            {
              "Name": "value",
              "Type": "System.Int64"
            }
          ],
          "ReturnType": "System.Void",
          "Visibility": "Public",
          "GenericParameter": []
        },
        {
          "Kind": "Method",
          "Name": "get_MaximumBodySize",
          "Parameters": [],
          "ReturnType": "System.Int64",
          "Visibility": "Public",
          "GenericParameter": []
        },
        {
          "Kind": "Method",
          "Name": "set_MaximumBodySize",
          "Parameters": [
            {
              "Name": "value",
              "Type": "System.Int64"
            }
          ],
          "ReturnType": "System.Void",
          "Visibility": "Public",
          "GenericParameter": []
        },
        {
          "Kind": "Method",
          "Name": "get_UseCaseSensitivePaths",
          "Parameters": [],
          "ReturnType": "System.Boolean",
          "Visibility": "Public",
          "GenericParameter": []
        },
        {
          "Kind": "Method",
          "Name": "set_UseCaseSensitivePaths",
          "Parameters": [
            {
              "Name": "value",
              "Type": "System.Boolean"
            }
          ],
          "ReturnType": "System.Void",
          "Visibility": "Public",
          "GenericParameter": []
        },
        {
          "Kind": "Constructor",
          "Name": ".ctor",
          "Parameters": [],
          "Visibility": "Public",
          "GenericParameter": []
        }
      ],
      "GenericParameters": []
    }
  ]
}