{
  "version": "1.0.0.0",
  "strings": {
    "name": "ASP.NET Core Web Uygulaması (Model-Görünüm-Denetleyici)",
    "description": "Örnek ASP.NET Core MVC Görünümleri ve Denetleyicileri içeren bir ASP.NET Core uygulaması oluşturmaya yönelik proje şablonu. Bu şablon aynı zamanda RESTful HTTP hizmetleri için de kullanılabilir.",
    "parameter.UseProgramMain.name": "_Üst düzey deyimler kullanmayın",
    "parameter.UseProgramMain.description": "Üst düzey deyimler yerine açık bir Program sınıfı ve Ana yöntem oluşturup oluşturulmayacağını belirtir."
  }
}