{
  "author": "Microsoft",
  "name": "Razor Class Library",
  "description": "A project for creating a Razor class library that targets .NET Standard",
  "symbols/Framework/description": "프로젝트에 대한 대상 프레임워크입니다.",
  "symbols/Framework/choices/net7.0/description": "대상 net7.0",
  "symbols/skipRestore/description": "지정된 경우, 프로젝트 생성 시 자동 복원을 건너뜁니다.",
  "symbols/SupportPagesAndViews/displayName": "Support pages and views",
  "symbols/SupportPagesAndViews/description": "Whether to support adding traditional Razor pages and Views in addition to components to this library.",
  "postActions/restore/description": "이 프로젝트에 필요한 NuGet 패키지를 복원합니다.",
  "postActions/restore/manualInstructions/default/text": "'dotnet restore' 실행",
  "postActions/openInEditor/description": "Opens Areas/MyFeature/Pages/Page1.cshtml in the editor"
}